lijingli/__init__.py
lijingli/main.py
lijingli-0.0.6.dist-info/LICENSE
lijingli-0.0.6.dist-info/METADATA
lijingli-0.0.6.dist-info/WHEEL
lijingli-0.0.6.dist-info/top_level.txt
lijingli-0.0.6.dist-info/RECORD
