Metadata-Version: 2.1
Name: lijingli
Version: 0.0.6
Author: JIa Junjie
Requires-Python: >=3.7
License-File: LICENSE
Requires-Dist: minepy ==1.2.6
